MANIFEST.in
NEWS.txt
README.macosx.txt
README.txt
REQUIREMENTS
setup.py
examples/Frenden6_1a_alt.tprx
examples/Frenden6_1a_darker.tprx
examples/Frenden6_1a_darkest.tprx
examples/eldpack_alt.tprx
examples/endpack_old_stone_2.tprx
examples/frenden-dark.tprx
examples/glossy.tprx
examples/groovystipple.tprx
examples/groovystipple_alt.tprx
examples/jolicraft-alt.tprx
examples/lucid-alts.tprx
examples/pixelade.tprx
examples/smoothstipple.tprx
examples/smoothstipple_alt.tprx
examples/stipple-alt.tprx
examples/GroovyStipple/font.txt
examples/GroovyStipple/news.txt
examples/GroovyStipple/pack.png
examples/GroovyStipple/pack.txt
examples/GroovyStipple/terrain.png
examples/GroovyStipple/armor/iron_1.png
examples/GroovyStipple/armor/iron_2.png
examples/GroovyStipple/art/kz.png
examples/GroovyStipple/environment/clouds.png
examples/GroovyStipple/font/default.png
examples/GroovyStipple/gui/background.png
examples/GroovyStipple/gui/container.png
examples/GroovyStipple/gui/crafting.png
examples/GroovyStipple/gui/furnace.png
examples/GroovyStipple/gui/gui.png
examples/GroovyStipple/gui/inventory.png
examples/GroovyStipple/gui/items.png
examples/GroovyStipple/gui/trap.png
examples/GroovyStipple/item/boat.png
examples/GroovyStipple/item/cart.png
examples/GroovyStipple/item/sign.png
examples/GroovyStipple/mob/cow.png
examples/GroovyStipple/mob/creeper.png
examples/GroovyStipple/mob/sheep.png
examples/GroovyStipple/mob/sheep_fur.png
examples/GroovyStipple/mob/zombie.png
examples/GroovyStipple/screenshots/groovystipple-1.png
examples/GroovyStipple/screenshots/groovystipple-2.png
examples/GroovyStipple/screenshots/groovystipple-3.png
examples/GroovyStipple/screenshots/groovystipple-4.png
examples/GroovyStipple/terrain/moon.png
examples/GroovyStipple/terrain/sun.png
examples/SmoothStipple/pack.png
examples/SmoothStipple/terrain.png
examples/maps/beta-12.tpmaps
examples/maps/beta-13.tpmaps
examples/maps/beta-14.tpmaps
examples/maps/beta-15.tpmaps
examples/maps/beta-16.tpmaps
src/texturepacker.egg-info/PKG-INFO
src/texturepacker.egg-info/SOURCES.txt
src/texturepacker.egg-info/dependency_links.txt
src/texturepacker.egg-info/requires.txt
src/texturepacker.egg-info/top_level.txt
