Metadata-Version: 1.0
Name: texturepacker
Version: 0.12
Summary: Assemble texture packs for Minecraft
Home-page: http://pdc.github.com/texturepacker/
Author: Damian Cugley
Author-email: pdc@alleged.org.uk
License: UNKNOWN
Platform: UNKNOWN
Classifier: Development Status :: 3 - Alpha
Classifier: Environment :: Console
Classifier: Framework :: Zope3
Classifier: Intended Audience :: Developers
Classifier: Intended Audience :: End Users/Desktop
Classifier: License :: OSI Approved :: GNU Library or Lesser General Public License (LGPL)
Classifier: Natural Language :: English
Classifier: Topic :: Games/Entertainment
Classifier: Topic :: Utilities
